{
  "timestamp": "2026-07-23T18:41:34.876237+08:00",
  "regime": "NEUTRAL",
  "score": 4,
  "reasons": [
    "DXY\u2191 (USD strength)",
    "VIX 18 (low vol)",
    "SPX\u2191 (risk-on)"
  ],
  "assets": {
    "DXY": {
      "price": 101.2,
      "chg_5d": 0.5
    },
    "VIX": {
      "price": 17.5,
      "chg_5d": 4.7
    },
    "SPX": {
      "price": 7499.0,
      "chg_5d": -1.0
    },
    "US10Y": {
      "price": 4.7,
      "chg_5d": 2.6
    },
    "BTC": {
      "price": 65748.1,
      "chg_5d": 1.5
    }
  },
  "horizon_matrix": {
    "W1": {
      "risk-on": "LONG",
      "neutral": "free",
      "risk-off": "SHORT"
    },
    "D1": {
      "risk-on": "LONG",
      "neutral": "free",
      "risk-off": "SHORT"
    },
    "D2": {
      "risk-on": "LONG",
      "neutral": "free",
      "risk-off": "SHORT"
    },
    "H4": {
      "risk-on": "LONG",
      "neutral": "free",
      "risk-off": "SHORT"
    },
    "H1": {
      "risk-on": "free",
      "neutral": "free",
      "risk-off": "free"
    },
    "M15": {
      "risk-on": "free",
      "neutral": "free",
      "risk-off": "free"
    }
  },
  "correlation": {
    "warnings": []
  },
  "news": [
    "\ud83d\udcc5 Initial Jobless Claims"
  ],
  "asset_list": {
    "XAUUSD": {
      "exchange": "OANDA",
      "type": "commodity",
      "session": "24h",
      "enabled_v4": true,
      "enabled_pam": true
    },
    "AAPL": {
      "exchange": "NASDAQ",
      "type": "stock",
      "session": "US",
      "enabled_v4": true,
      "enabled_pam": true
    },
    "META": {
      "exchange": "NASDAQ",
      "type": "stock",
      "session": "US",
      "enabled_v4": true,
      "enabled_pam": true
    },
    "GOOGL": {
      "exchange": "NASDAQ",
      "type": "stock",
      "session": "US",
      "enabled_v4": true,
      "enabled_pam": true
    },
    "MSFT": {
      "exchange": "NASDAQ",
      "type": "stock",
      "session": "US",
      "enabled_v4": true,
      "enabled_pam": true
    }
  }
}